include/blosc2_grok.h
include/grok-11.0/grok.h
include/grok-11.0/grk_config.h
blosc2_grok/__init__.py
blosc2_grok/libblosc2_grok.so
lib/libgrokj2k.a
blosc2_grok-0.3.3.dist-info/RECORD
blosc2_grok-0.3.3.dist-info/WHEEL
blosc2_grok-0.3.3.dist-info/entry_points.txt
blosc2_grok-0.3.3.dist-info/METADATA
blosc2_grok-0.3.3.dist-info/licenses/LICENSE.txt
