Metadata-Version: 2.1
Name: blosc2_grok
Version: 0.3.3
Summary: Grok (JPEG2000 codec) plugin for Blosc2.
Keywords: plugin blosc2
Author-Email: Blosc Development Team <contact@blosc.org>
License: GNU Affero General Public License version 3
Classifier: Programming Language :: Python :: 3
Classifier: Programming Language :: C
Classifier: Programming Language :: C++
Classifier: Development Status :: 3 - Alpha
Classifier: Intended Audience :: Developers
Classifier: Intended Audience :: Information Technology
Classifier: License :: OSI Approved :: GNU Affero General Public License v3 or later (AGPLv3+)
Classifier: Topic :: Software Development :: Libraries :: Python Modules
Classifier: Topic :: System :: Archiving :: Compression
Classifier: Operating System :: Microsoft :: Windows
Classifier: Operating System :: Unix
Project-URL: Homepage, https://github.com/Blosc/blosc2_grok
Project-URL: Issues, https://github.com/Blosc/blosc2_grok/issues
Requires-Dist: blosc2
Requires-Dist: pytest; extra == "h5py-test"
Provides-Extra: h5py-test
License-File: LICENSE.txt
